inseminator/__init__.py
inseminator/container.py
inseminator/decorator.py
inseminator/dependency.py
inseminator/exceptions.py
inseminator/integrations/__init__.py
inseminator/integrations/celery.py
inseminator/metrics.py
inseminator/py.typed
inseminator/resolver.py
inseminator/scoped_dict.py
inseminator-0.4.7.dist-info/WHEEL
inseminator-0.4.7.dist-info/METADATA
inseminator-0.4.7.dist-info/RECORD
