Metadata-Version: 2.1
Name: inseminator
Version: 0.4.7
Summary: Python dependency injection library based on type hints
Home-page: https://www.github.com/sukovanej/inseminator/
Keywords: DI,dependency injection
Author: Milan Suk
Author-email: Milansuk@email.cz
Requires-Python: >=3.8,<4.0
Classifier: Development Status :: 5 - Production/Stable
Classifier: Environment :: Console
Classifier: License :: OSI Approved :: MIT License
Classifier: Operating System :: OS Independent
Classifier: Programming Language :: Python :: 3
Classifier: Programming Language :: Python :: 3.10
Classifier: Programming Language :: Python :: 3.8
Classifier: Programming Language :: Python :: 3.9
Classifier: Topic :: Software Development :: Libraries
Requires-Dist: pydantic (>=1.8.2,<2.0.0)
Project-URL: Documentation, https://www.github.com/sukovanej/inseminator/
Project-URL: Repository, https://www.github.com/sukovanej/inseminator/
